setup.py
enigma/__init__.py
enigma/enigma.py
enigma_xd.egg-info/PKG-INFO
enigma_xd.egg-info/SOURCES.txt
enigma_xd.egg-info/dependency_links.txt
enigma_xd.egg-info/top_level.txt