Metadata-Version: 2.1
Name: enigma-xd
Version: 0.0.0
Summary: enigma - the message is gone forever
Home-page: https://github.com/kishalxd/enigma
Author: Kishal Mandal
Author-email: km.kkishal@gmail.com
License: Apache License
Platform: linux
Platform: unix
Requires-Python: >=3.6
